cli_skel/__init__.py
cli_skel/argparse_skel.py
cli_skel/cmd_skel.py
cli_skel/utils/__init__.py
cli_skel/utils/context_utils.py
cli_skel/utils/result.py
cli_skel/utils/sentinels.py
cli_skel-0.4.0.dist-info/LICENSE
cli_skel-0.4.0.dist-info/METADATA
cli_skel-0.4.0.dist-info/WHEEL
cli_skel-0.4.0.dist-info/top_level.txt
cli_skel-0.4.0.dist-info/RECORD
