Metadata-Version: 2.1
Name: cli-skel
Version: 0.4.0
Summary: Generate CLI applications from python dictionaries.
Author-email: Michael Frank <frankm@post.bgu.ac.il>
Maintainer-email: Michael Frank <frankm@post.bgu.ac.il>
License: MIT License
Project-URL: Homepage, https://github.com/michael-123123/cli-skel
Project-URL: Repository, https://github.com/michael-123123/cli-skel.git
Project-URL: Issues, https://github.com/michael-123123/cli-skel/issues
Keywords: cli,argparse,cmd,repl
Classifier: Programming Language :: Python
Classifier: Programming Language :: Python :: 3
Classifier: Programming Language :: Python :: 3.12
Classifier: Development Status :: 5 - Production/Stable
Classifier: Intended Audience :: Developers
Classifier: Topic :: Software Development :: Interpreters
Classifier: Topic :: Software Development :: Libraries
Classifier: Topic :: Terminals
Classifier: Topic :: Utilities
Requires-Python: >=3.12
License-File: LICENSE
Provides-Extra: dev
Requires-Dist: pytest ; extra == 'dev'
Requires-Dist: pytest-cov ; extra == 'dev'
Requires-Dist: jupyter ; extra == 'dev'
Requires-Dist: myst-nb ; extra == 'dev'
Requires-Dist: sphinx-autoapi ; extra == 'dev'
Requires-Dist: sphinx-rtd-theme ; extra == 'dev'
Requires-Dist: sphinx-markdown-builder ; extra == 'dev'
Requires-Dist: tomlkit ; extra == 'dev'
